{
  "updated_at": "2026-07-17T23:11:05Z",
  "policy": "phase7_official_collection_status_v1",
  "summary": {
    "status": "waiting_sources",
    "configured_source_count": 4,
    "enabled_source_count": 2,
    "successful_source_count": 2,
    "failed_source_count": 0,
    "raw_count": 0,
    "valid_count": 0,
    "rejected_count": 0,
    "snapshot_preserved": true
  },
  "sources": [
    {
      "source_id": "REAL_OFFICIAL_API_OUTPUT",
      "provider": "KOSIS·공공데이터포털",
      "adapter": "local_json",
      "enabled": true,
      "status": "empty",
      "fetched_count": 0,
      "valid_count": 0,
      "rejected_count": 0,
      "message": "수집 대상 레코드 없음"
    },
    {
      "source_id": "ADMIN_APPROVED_MANUAL",
      "provider": "HESEB 관리자 승인",
      "adapter": "local_json",
      "enabled": true,
      "status": "empty",
      "fetched_count": 0,
      "valid_count": 0,
      "rejected_count": 0,
      "message": "수집 대상 레코드 없음"
    },
    {
      "source_id": "LEGACY_KOSIS_FULL_URL",
      "provider": "국가통계포털 KOSIS",
      "adapter": "remote_json",
      "enabled": false,
      "status": "disabled",
      "fetched_count": 0,
      "valid_count": 0,
      "rejected_count": 0,
      "message": "Phase 8의 세분화된 KOSIS 연결로 대체"
    },
    {
      "source_id": "LEGACY_DATA_GO_KR_FULL_URL",
      "provider": "공공데이터포털",
      "adapter": "remote_json",
      "enabled": false,
      "status": "disabled",
      "fetched_count": 0,
      "valid_count": 0,
      "rejected_count": 0,
      "message": "Phase 8의 실제 소스 연결로 대체"
    }
  ],
  "rejected": [],
  "notice": "신규 유효 데이터가 0건이면 기존 Clean/Snapshot/History를 보존합니다."
}
