{
  "updated_at": "2026-07-19T00:12:33Z",
  "policy": "phase2_admin_log_v3_sanitized",
  "summary": {
    "raw_count": 136,
    "clean_count": 136,
    "rejected_count": 0,
    "duplicate_count": 2,
    "official_count": 62,
    "average_quality": 73
  },
  "by_species": {
    "EGG": 36,
    "BEEF": 29,
    "POULTRY": 22,
    "PORK": 39,
    "OTHER": 31,
    "DUCK": 1
  },
  "by_evidence_type": {
    "일반": 35,
    "가격": 20,
    "정책/고시": 5,
    "질병/방역": 53,
    "수급/도축": 15,
    "수요/행사": 8
  },
  "by_evidence_axis": {
    "news": 43,
    "price": 20,
    "policy": 5,
    "disease": 53,
    "supply": 15
  },
  "recent_rejections": []
}
