{
  "updated_at": "2026-07-18T00:12:25Z",
  "policy": "phase2_admin_log_v3_sanitized",
  "summary": {
    "raw_count": 139,
    "clean_count": 139,
    "rejected_count": 0,
    "duplicate_count": 3,
    "official_count": 62,
    "average_quality": 74
  },
  "by_species": {
    "EGG": 37,
    "BEEF": 29,
    "PORK": 41,
    "POULTRY": 23,
    "OTHER": 32,
    "DUCK": 1
  },
  "by_evidence_type": {
    "일반": 33,
    "정책/고시": 5,
    "가격": 19,
    "질병/방역": 54,
    "수급/도축": 18,
    "수요/행사": 10
  },
  "by_evidence_axis": {
    "news": 43,
    "policy": 5,
    "price": 19,
    "disease": 54,
    "supply": 18
  },
  "recent_rejections": []
}
